crypto_com_agent_plugin_sqlite/__init__.py
crypto_com_agent_plugin_sqlite/main.py
crypto_com_agent_plugin_sqlite/utils/sanitize.py
cryptocom_agent_plugin_sqlite-1.0.4.dist-info/METADATA
cryptocom_agent_plugin_sqlite-1.0.4.dist-info/WHEEL
cryptocom_agent_plugin_sqlite-1.0.4.dist-info/entry_points.txt
cryptocom_agent_plugin_sqlite-1.0.4.dist-info/RECORD
