Metadata-Version: 2.4
Name: cryptocom_agent_plugin_sqlite
Version: 1.0.4
Summary: SQLite plugin for Crypto.com Agent Client
Author: Ric Arcifa
Author-email: ricardo.arcifa@crypto.com
Requires-Python: >=3.12,<4.0
Classifier: Programming Language :: Python :: 3
Classifier: Programming Language :: Python :: 3.12
Classifier: Programming Language :: Python :: 3.13
Classifier: Programming Language :: Python :: 3.14
Requires-Dist: cryptocom-agent-client (>=1.2.1)
Requires-Dist: langchain-core (>=0.3.55)
